relevance_connect/__init__.py
relevance_connect/cli.py
relevance_connect/login.py
relevance_connect/logout.py
relevance_connect/run.py
relevance_connect/run_js.py
relevance_connect/save.py
relevance_connect/core/__init__.py
relevance_connect/core/auth.py
relevance_connect/core/relevance_code.py
relevance_connect-0.1.1.dist-info/licenses/LICENSE
relevance_connect-0.1.1.dist-info/METADATA
relevance_connect-0.1.1.dist-info/WHEEL
relevance_connect-0.1.1.dist-info/entry_points.txt
relevance_connect-0.1.1.dist-info/top_level.txt
relevance_connect-0.1.1.dist-info/RECORD
