Metadata-Version: 2.4
Name: relevance_connect
Version: 0.1.1
Home-page: https://relevanceai.com/
Author: Relevance AI
Author-email: jacky@relevanceai.com
License-File: LICENSE
Requires-Dist: requests
Dynamic: author
Dynamic: author-email
Dynamic: description
Dynamic: description-content-type
Dynamic: home-page
Dynamic: license-file
Dynamic: requires-dist
